Metadata-Version: 2.1
Name: flairaio
Version: 0.2.0
Summary: Asynchronous Python library for Flair's API
Home-page: https://github.com/RobertD502/flairaio
Author: Robert Drinovac
Author-email: unlisted@gmail.com
Project-URL: Bug Reports, https://github.com/RobertD502/flairaio/issues
Project-URL: Source, https://github.com/RobertD502/flairaio/
Keywords: flair,flair systems,flair api,flair api oauth2,flair client,flair vent,flair puck,flair bridge
Classifier: Programming Language :: Python :: 3
Classifier: License :: OSI Approved :: MIT License
Classifier: Operating System :: OS Independent
Requires-Python: >=3.7
License-File: LICENSE
Requires-Dist: aiohttp>=3.8.1
